llama_index/embeddings/huggingface_api/__init__.py
llama_index/embeddings/huggingface_api/base.py
llama_index/embeddings/huggingface_api/pooling.py
llama_index_embeddings_huggingface_api-0.4.1.dist-info/METADATA
llama_index_embeddings_huggingface_api-0.4.1.dist-info/WHEEL
llama_index_embeddings_huggingface_api-0.4.1.dist-info/licenses/LICENSE
llama_index_embeddings_huggingface_api-0.4.1.dist-info/RECORD
